garmin_ical_export-1.1.1.dist-info/licenses/LICENSE
garminicalexport/__init__.py
garminicalexport/activities.py
garminicalexport/cmd.py
garminicalexport/data_types.py
garminicalexport/format_utils.py
garminicalexport/garmin_api.py
garmin_ical_export-1.1.1.dist-info/METADATA
garmin_ical_export-1.1.1.dist-info/WHEEL
garmin_ical_export-1.1.1.dist-info/entry_points.txt
garmin_ical_export-1.1.1.dist-info/top_level.txt
garmin_ical_export-1.1.1.dist-info/RECORD
