Metadata-Version: 2.4
Name: garmin-ical-export
Version: 1.1.1
Summary: Export Garmin Connect activities to iCalendar file
Home-page: https://github.com/jirikuchta/garmin-ical-export
Author: Jiri Kuchta
Author-email: jiri.kuchta@email.cz
License: MIT
Requires-Python: >=3.8
License-File: LICENSE
Requires-Dist: vobject
Requires-Dist: garth
Dynamic: author
Dynamic: author-email
Dynamic: description
Dynamic: description-content-type
Dynamic: home-page
Dynamic: license
Dynamic: license-file
Dynamic: requires-dist
Dynamic: requires-python
Dynamic: summary
